tfAugmentor/Augmentor.py
tfAugmentor/__init__.py
tfAugmentor/color.py
tfAugmentor/gaussian.py
tfAugmentor/operations.py
tfAugmentor/warp.py
tfAugmentor-1.3.2.dist-info/LICENSE
tfAugmentor-1.3.2.dist-info/METADATA
tfAugmentor-1.3.2.dist-info/WHEEL
tfAugmentor-1.3.2.dist-info/top_level.txt
tfAugmentor-1.3.2.dist-info/RECORD
