Metadata-Version: 2.1
Name: tfAugmentor
Version: 1.3.2
Summary: An image augmentation library for tensorflow. Easy use with tf.data.Dataset
Home-page: https://github.com/looooongChen/tfAugmentor
Author: Long Chen
Author-email: looooong.chen@gmail.com
License: UNKNOWN
Platform: UNKNOWN
Classifier: Programming Language :: Python :: 3
Classifier: License :: OSI Approved :: MIT License
Classifier: Operating System :: OS Independent
License-File: LICENSE
Requires-Dist: tensorflow (>=2.0.0)
Requires-Dist: numpy
